bs_gl_client-0.2.0.dist-info/METADATA
bs_gl_client-0.2.0.dist-info/WHEEL
glclient/greenlight_pb2.pyi
glclient/rpc.py
glclient/scheduler_pb2.pyi
glclient/scheduler_pb2.py
glclient/greenlight_pb2_grpc.py
glclient/__init__.py
glclient/py.typed
glclient/lsps.py
glclient/glclient.pyi
glclient/greenlight_pb2_grpc.pyi
glclient/greenlight_pb2.py
glclient/tls.py
glclient/scheduler_pb2_grpc.py
glclient/glclient.abi3.so
bs_gl_client-0.2.0.dist-info/RECORD
